iotile_support_exec_nrf52832_3/__init__.py
iotile_support_exec_nrf52832_3/nrf52832_safemode.py
iotile_support_exec_nrf52832_3-3.1.3.dist-info/METADATA
iotile_support_exec_nrf52832_3-3.1.3.dist-info/WHEEL
iotile_support_exec_nrf52832_3-3.1.3.dist-info/entry_points.txt
iotile_support_exec_nrf52832_3-3.1.3.dist-info/top_level.txt
iotile_support_exec_nrf52832_3-3.1.3.dist-info/RECORD
